Metadata-Version: 2.1
Name: myValues
Version: 0.1.29
Summary: 包含常用的许多值，为程序制作提供便利。
Home-page: https://code.xueersi.com
Author: Ruoyu Wang
Author-email: wangruoyu666@outlook.com
License: UNKNOWN
Platform: UNKNOWN
